topsis/__init__.py
topsis/topsis.py
topsis_swastik_102303585-1.0.5.dist-info/licenses/LICENSE
topsis_swastik_102303585-1.0.5.dist-info/METADATA
topsis_swastik_102303585-1.0.5.dist-info/WHEEL
topsis_swastik_102303585-1.0.5.dist-info/entry_points.txt
topsis_swastik_102303585-1.0.5.dist-info/top_level.txt
topsis_swastik_102303585-1.0.5.dist-info/RECORD
