Metadata-Version: 2.4
Name: topsis-swastik-102303585
Version: 1.0.5
Summary: TOPSIS algorithm as a command-line tool
Author-email: Swastik Nagpal <nagpalswastik@gmail.com>
License: MIT
Keywords: topsis,mcdm,decision-making,cli
Classifier: License :: OSI Approved :: MIT License
Classifier: Programming Language :: Python :: 3
Classifier: Programming Language :: Python :: 3 :: Only
Classifier: Operating System :: OS Independent
Requires-Python: >=3.7
License-File: LICENSE
Requires-Dist: pandas
Requires-Dist: numpy
Dynamic: license-file
